pad/pad.v
module pad(
    //DIN, pad driver when pad configured as output
    //OEN, pad direction(1-input, o-output)
    input        DIN, OEN ,
    //pull function (00,01-dispull, 10-pullup, 11-pulldown)
    input [1:0]  PULL ,
    inout        PAD ,
    //pad load when pad configured as input
    output reg   DOUT
    );
 
    //input:(not effect pad external input logic), output: DIN->PAD
    assign       PAD = OEN? 'bz : DIN ;
 
    //input:(PAD->DOUT)
    always @(*) begin
        if (OEN == 1) begin //input
            DOUT   = PAD ;
        end
        else begin
            DOUT   = 'bz ;
        end
    end
 
    //use tristate gate in Verilog to realize pull up/down function
    bufif1  puller(PAD, PULL[0], PULL[1]);
 
endmodule

pad/test.sv
`timescale 1ns/1ns
 
module test ;
    reg          DIN, OEN ;
    reg [1:0]    PULL ;
    wire         PAD ;
    wire         DOUT ;
 
    reg          PAD_REG ;
    assign       PAD = OEN ? PAD_REG : 1'bz ; //
 
    initial begin
        PAD_REG   = 1'bz ;        //pad with no dirve at first
        OEN       = 1'b1 ;        //input simulation
        #0 ;      PULL      = 2'b10 ;   //pull down
        #20 ;     PULL      = 2'b11 ;   //pull up
        #20 ;     PULL      = 2'b00 ;   //dispull
        #20 ;     PAD_REG   = 1'b0 ;
        #20 ;     PAD_REG   = 1'b1 ;
 
        #30 ;     OEN       = 1'b0 ;    //output simulation
                  DIN       = 1'bz ;
        #15 ;     DIN       = 1'b0 ;
        #15 ;     DIN       = 1'b1 ;
    end
 
    pad     u_pad(
        .DIN     (DIN) ,
        .OEN     (OEN) ,
        .PULL    (PULL) ,
        .PAD     (PAD) ,
        .DOUT    (DOUT)
    );
 
    initial begin
        forever begin
            #100;
            if ($time >= 1000)  $finish ;
        end
    end

    //iverilog
    initial begin
        $dumpfile("wave.vcd");
        $dumpvars(0,test);
    end
 
endmodule // test

pad/wave.vcd
$date
	Tue May 17 17:03:57 2022
$end
$version
	Icarus Verilog
$end
$timescale
	1ns
$end
$scope module test $end
$var wire 1 ! PAD $end
$var wire 1 " DOUT $end
$var reg 1 # DIN $end
$var reg 1 $ OEN $end
$var reg 1 % PAD_REG $end
$var reg 2 & PULL [1:0] $end
$scope module u_pad $end
$var wire 1 # DIN $end
$var wire 1 $ OEN $end
$var wire 1 ! PAD $end
$var wire 2 ' PULL [1:0] $end
$var reg 1 " DOUT $end
$upscope $end
$upscope $end
$enddefinitions $end
#0
$dumpvars
b10 '
b10 &
z%
1$
x#
0"
0!
$end
#20
1"
1!
b11 &
b11 '
#40
z"
z!
b0 &
b0 '
#60
0"
0!
0%
#80
1"
1!
1%
#110
z!
z"
z#
0$
#125
0!
0#
#140
1!
1#
